Workbook

Sheet Bank_Statement
A1: Date | B1: Transaction_ID | C1: Description | D1: Debit | E1: Credit | F1: Balance | H1: Match Status
A2: 01-04-2026 | B2: TXN1000 | C2: UTILITY BILL | D2: 3953 | F2: 46047 | H2: =IF(ISNA(VLOOKUP(B2,Cash_Book!B:B,1,FALSE)),"Missing","Found") -> Missing
A3: 02-04-2026 | B3: TXN1001 | C3: CLIENT PAYMENT | E3: 9769 | F3: 55816 | H3: =IF(ISNA(VLOOKUP(B3,Cash_Book!B:D,2,FALSE)),"Missing","Found") -> Found
A4: 03-04-2026 | B4: TXN1002 | C4: EFT PAYMENT | D4: 4142 | F4: 51674 | H4: =IF(ISNA(VLOOKUP(B4,Cash_Book!B:D,2,FALSE)),"Missing","Found") -> Found
A5: 04-04-2026 | B5: TXN1003 | C5: EFT RECEIPT | E5: 4282 | F5: 55956 | H5: =IF(ISNA(VLOOKUP(B5,Cash_Book!B:D,2,FALSE)),"Missing","Found") -> Found
A6: 05-04-2026 | B6: TXN1004 | C6: SALARY CREDIT | E6: 8715 | F6: 64671 | H6: =IF(ISNA(VLOOKUP(B6,Cash_Book!B:D,2,FALSE)),"Missing","Found") -> Found
A7: 06-04-2026 | B7: TXN1005 | C7: UPI RECEIPT | E7: 7433 | F7: 72104 | H7: =IF(ISNA(VLOOKUP(B7,Cash_Book!B:D,2,FALSE)),"Missing","Found") -> Found
A8: 07-04-2026 | B8: TXN1006 | C8: ATM WITHDRAWAL | D8: 4347 | F8: 67757 | H8: =IF(ISNA(VLOOKUP(B8,Cash_Book!B:D,2,FALSE)),"Missing","Found") -> Found
A9: 08-04-2026 | B9: TXN1007 | C9: BANK FEES | D9: 4463 | F9: 63294 | H9: =IF(ISNA(VLOOKUP(B9,Cash_Book!B:D,2,FALSE)),"Missing","Found") -> Found
A10: 09-04-2026 | B10: TXN1008 | C10: NEFT CREDIT | E10: 7717 | F10: 71011 | H10: =IF(ISNA(VLOOKUP(B10,Cash_Book!B:D,2,FALSE)),"Missing","Found") -> Found
A11: 10-04-2026 | B11: TXN1009 | C11: NEFT CREDIT | E11: 4562 | F11: 75573 | H11: =IF(ISNA(VLOOKUP(B11,Cash_Book!B:D,2,FALSE)),"Missing","Found") -> Found
A12: 11-04-2026 | B12: TXN1010 | C12: SALARY CREDIT | E12: 3826 | F12: 79399 | H12: =IF(ISNA(VLOOKUP(B12,Cash_Book!B:D,2,FALSE)),"Missing","Found") -> Found
A13: 12-04-2026 | B13: TXN1011 | C13: EFT PAYMENT | D13: 6010 | F13: 73389 | H13: =IF(ISNA(VLOOKUP(B13,Cash_Book!B:D,2,FALSE)),"Missing","Found") -> Found
A14: 13-04-2026 | B14: TXN1012 | C14: NEFT CREDIT | E14: 1679 | F14: 75068 | H14: =IF(ISNA(VLOOKUP(B14,Cash_Book!B:D,2,FALSE)),"Missing","Found") -> Found
A15: 14-04-2026 | B15: TXN1013 | C15: BANK FEES | D15: 738 | F15: 74330 | H15: =IF(ISNA(VLOOKUP(B15,Cash_Book!B:D,2,FALSE)),"Missing","Found") -> Found
A16: 15-04-2026 | B16: TXN1014 | C16: BANK FEES | D16: 726 | F16: 73604 | H16: =IF(ISNA(VLOOKUP(B16,Cash_Book!B:D,2,FALSE)),"Missing","Found") -> Found
A17: 16-04-2026 | B17: TXN1015 | C17: SALARY CREDIT | E17: 4261 | F17: 77865 | H17: =IF(ISNA(VLOOKUP(B17,Cash_Book!B:D,2,FALSE)),"Missing","Found") -> Missing
A18: 17-04-2026 | B18: TXN1016 | C18: ATM WITHDRAWAL | D18: 327 | F18: 77538 | H18: =IF(ISNA(VLOOKUP(B18,Cash_Book!B:D,2,FALSE)),"Missing","Found") -> Found
A19: 18-04-2026 | B19: TXN1017 | C19: SALARY CREDIT | E19: 9248 | F19: 86786 | H19: =IF(ISNA(VLOOKUP(B19,Cash_Book!B:D,2,FALSE)),"Missing","Found") -> Found
A20: 19-04-2026 | B20: TXN1018 | C20: NEFT CREDIT | E20: 1750 | F20: 88536 | H20: =IF(ISNA(VLOOKUP(B20,Cash_Book!B:D,2,FALSE)),"Missing","Found") -> Found
A21: 20-04-2026 | B21: TXN1019 | C21: EFT RECEIPT | E21: 4600 | F21: 93136 | H21: =IF(ISNA(VLOOKUP(B21,Cash_Book!B:D,2,FALSE)),"Missing","Found") -> Found
A22: 21-04-2026 | B22: TXN1020 | C22: CLIENT PAYMENT | E22: 4978 | F22: 98114 | H22: =IF(ISNA(VLOOKUP(B22,Cash_Book!B:D,2,FALSE)),"Missing","Found") -> Found
A23: 22-04-2026 | B23: TXN1021 | C23: EFT PAYMENT | D23: 5630 | F23: 92484 | H23: =IF(ISNA(VLOOKUP(B23,Cash_Book!B:D,2,FALSE)),"Missing","Found") -> Found
A24: 23-04-2026 | B24: TXN1022 | C24: CHEQUE PAYMENT | D24: 3885 | F24: 88599 | H24: =IF(ISNA(VLOOKUP(B24,Cash_Book!B:D,2,FALSE)),"Missing","Found") -> Found
A25: 24-04-2026 | B25: TXN1023 | C25: BANK FEES | D25: 4845 | F25: 83754 | H25: =IF(ISNA(VLOOKUP(B25,Cash_Book!B:D,2,FALSE)),"Missing","Found") -> Found
A26: 25-04-2026 | B26: TXN1024 | C26: NEFT CREDIT | E26: 5343 | F26: 89097 | H26: =IF(ISNA(VLOOKUP(B26,Cash_Book!B:D,2,FALSE)),"Missing","Found") -> Found
A27: 26-04-2026 | B27: TXN1025 | C27: ATM WITHDRAWAL | D27: 5245 | F27: 83852 | H27: =IF(ISNA(VLOOKUP(B27,Cash_Book!B:D,2,FALSE)),"Missing","Found") -> Found
A28: 27-04-2026 | B28: TXN1026 | C28: SALARY CREDIT | E28: 1936 | F28: 85788 | H28: =IF(ISNA(VLOOKUP(B28,Cash_Book!B:D,2,FALSE)),"Missing","Found") -> Found
A29: 28-04-2026 | B29: TXN1027 | C29: SALARY CREDIT | E29: 8843 | F29: 94631 | H29: =IF(ISNA(VLOOKUP(B29,Cash_Book!B:D,2,FALSE)),"Missing","Found") -> Found
A30: 29-04-2026 | B30: TXN1028 | C30: UTILITY BILL | D30: 4804 | F30: 89827 | H30: =IF(ISNA(VLOOKUP(B30,Cash_Book!B:D,2,FALSE)),"Missing","Found") -> Found
A31: 30-04-2026 | B31: TXN1029 | C31: UPI RECEIPT | E31: 570 | F31: 90397 | H31: =IF(ISNA(VLOOKUP(B31,Cash_Book!B:D,2,FALSE)),"Missing","Found") -> Found
A32: 01-04-2026 | B32: TXN1030 | C32: UPI RECEIPT | E32: 7936 | F32: 98333 | H32: =IF(ISNA(VLOOKUP(B32,Cash_Book!B:D,2,FALSE)),"Missing","Found") -> Missing
A33: 02-04-2026 | B33: TXN1031 | C33: ATM WITHDRAWAL | D33: 4087 | F33: 94246 | H33: =IF(ISNA(VLOOKUP(B33,Cash_Book!B:D,2,FALSE)),"Missing","Found") -> Found
A34: 03-04-2026 | B34: TXN1032 | C34: EFT RECEIPT | E34: 5948 | F34: 100194 | H34: =IF(ISNA(VLOOKUP(B34,Cash_Book!B:D,2,FALSE)),"Missing","Found") -> Found
A35: 04-04-2026 | B35: TXN1033 | C35: NEFT CREDIT | E35: 1423 | F35: 101617 | H35: =IF(ISNA(VLOOKUP(B35,Cash_Book!B:D,2,FALSE)),"Missing","Found") -> Found
A36: 05-04-2026 | B36: TXN1034 | C36: SALARY CREDIT | E36: 1766 | F36: 103383 | H36: =IF(ISNA(VLOOKUP(B36,Cash_Book!B:D,2,FALSE)),"Missing","Found") -> Found
A37: 06-04-2026 | B37: TXN1035 | C37: EFT PAYMENT | D37: 7757 | F37: 95626 | H37: =IF(ISNA(VLOOKUP(B37,Cash_Book!B:D,2,FALSE)),"Missing","Found") -> Found
A38: 07-04-2026 | B38: TXN1036 | C38: BANK FEES | D38: 3449 | F38: 92177 | H38: =IF(ISNA(VLOOKUP(B38,Cash_Book!B:D,2,FALSE)),"Missing","Found") -> Found
A39: 08-04-2026 | B39: TXN1037 | C39: CHEQUE PAYMENT | D39: 2936 | F39: 89241 | H39: =IF(ISNA(VLOOKUP(B39,Cash_Book!B:D,2,FALSE)),"Missing","Found") -> Found
A40: 09-04-2026 | B40: TXN1038 | C40: ATM WITHDRAWAL | D40: 7530 | F40: 81711 | H40: =IF(ISNA(VLOOKUP(B40,Cash_Book!B:D,2,FALSE)),"Missing","Found") -> Found
A41: 10-04-2026 | B41: TXN1039 | C41: SALARY CREDIT | E41: 6404 | F41: 88115 | H41: =IF(ISNA(VLOOKUP(B41,Cash_Book!B:D,2,FALSE)),"Missing","Found") -> Found
A42: 11-04-2026 | B42: TXN1040 | C42: UTILITY BILL | D42: 4145 | F42: 83970 | H42: =IF(ISNA(VLOOKUP(B42,Cash_Book!B:D,2,FALSE)),"Missing","Found") -> Found
A43: 12-04-2026 | B43: TXN1041 | C43: CLIENT PAYMENT | E43: 9274 | F43: 93244 | H43: =IF(ISNA(VLOOKUP(B43,Cash_Book!B:D,2,FALSE)),"Missing","Found") -> Found
A44: 13-04-2026 | B44: TXN1042 | C44: BANK FEES | D44: 684 | F44: 92560 | H44: =IF(ISNA(VLOOKUP(B44,Cash_Book!B:D,2,FALSE)),"Missing","Found") -> Found
A45: 14-04-2026 | B45: TXN1043 | C45: SALARY CREDIT | E45: 4307 | F45: 96867 | H45: =IF(ISNA(VLOOKUP(B45,Cash_Book!B:D,2,FALSE)),"Missing","Found") -> Found
A46: 15-04-2026 | B46: TXN1044 | C46: NEFT CREDIT | E46: 2549 | F46: 99416 | H46: =IF(ISNA(VLOOKUP(B46,Cash_Book!B:D,2,FALSE)),"Missing","Found") -> Found
A47: 16-04-2026 | B47: TXN1045 | C47: UTILITY BILL | D47: 1931 | F47: 97485 | H47: =IF(ISNA(VLOOKUP(B47,Cash_Book!B:D,2,FALSE)),"Missing","Found") -> Missing
A48: 17-04-2026 | B48: TXN1046 | C48: BANK FEES | D48: 4296 | F48: 93189 | H48: =IF(ISNA(VLOOKUP(B48,Cash_Book!B:D,2,FALSE)),"Missing","Found") -> Found
A49: 18-04-2026 | B49: TXN1047 | C49: CHEQUE PAYMENT | D49: 2986 | F49: 90203 | H49: =IF(ISNA(VLOOKUP(B49,Cash_Book!B:D,2,FALSE)),"Missing","Found") -> Found
A50: 19-04-2026 | B50: TXN1048 | C50: EFT RECEIPT | E50: 7153 | F50: 97356 | H50: =IF(ISNA(VLOOKUP(B50,Cash_Book!B:D,2,FALSE)),"Missing","Found") -> Found
A51: 20-04-2026 | B51: TXN1049 | C51: NEFT CREDIT | E51: 2656 | F51: 100012 | H51: =IF(ISNA(VLOOKUP(B51,Cash_Book!B:D,2,FALSE)),"Missing","Found") -> Found
A52: 21-04-2026 | B52: TXN1050 | C52: BANK FEES | D52: 7823 | F52: 92189 | H52: =IF(ISNA(VLOOKUP(B52,Cash_Book!B:D,2,FALSE)),"Missing","Found") -> Found
A53: 22-04-2026 | B53: TXN1051 | C53: UPI RECEIPT | E53: 1044 | F53: 93233 | H53: =IF(ISNA(VLOOKUP(B53,Cash_Book!B:D,2,FALSE)),"Missing","Found") -> Found
A54: 23-04-2026 | B54: TXN1052 | C54: UTILITY BILL | D54: 4878 | F54: 88355 | H54: =IF(ISNA(VLOOKUP(B54,Cash_Book!B:D,2,FALSE)),"Missing","Found") -> Found
A55: 24-04-2026 | B55: TXN1053 | C55: UTILITY BILL | D55: 2999 | F55: 85356 | H55: =IF(ISNA(VLOOKUP(B55,Cash_Book!B:D,2,FALSE)),"Missing","Found") -> Found
A56: 25-04-2026 | B56: TXN1054 | C56: EFT PAYMENT | D56: 3409 | F56: 81947 | H56: =IF(ISNA(VLOOKUP(B56,Cash_Book!B:D,2,FALSE)),"Missing","Found") -> Found
A57: 26-04-2026 | B57: TXN1055 | C57: UTILITY BILL | D57: 2187 | F57: 79760 | H57: =IF(ISNA(VLOOKUP(B57,Cash_Book!B:D,2,FALSE)),"Missing","Found") -> Found
A58: 27-04-2026 | B58: TXN1056 | C58: CHEQUE PAYMENT | D58: 4962 | F58: 74798 | H58: =IF(ISNA(VLOOKUP(B58,Cash_Book!B:D,2,FALSE)),"Missing","Found") -> Found
A59: 28-04-2026 | B59: TXN1057 | C59: CHEQUE PAYMENT | D59: 846 | F59: 73952 | H59: =IF(ISNA(VLOOKUP(B59,Cash_Book!B:D,2,FALSE)),"Missing","Found") -> Found
A60: 29-04-2026 | B60: TXN1058 | C60: NEFT CREDIT | E60: 3653 | F60: 77605 | H60: =IF(ISNA(VLOOKUP(B60,Cash_Book!B:D,2,FALSE)),"Missing","Found") -> Found
A61: 30-04-2026 | B61: TXN1059 | C61: EFT RECEIPT | E61: 7892 | F61: 85497 | H61: =IF(ISNA(VLOOKUP(B61,Cash_Book!B:D,2,FALSE)),"Missing","Found") -> Found
A62: 01-04-2026 | B62: TXN1060 | C62: EFT RECEIPT | E62: 9024 | F62: 94521 | H62: =IF(ISNA(VLOOKUP(B62,Cash_Book!B:D,2,FALSE)),"Missing","Found") -> Missing
A63: 02-04-2026 | B63: TXN1061 | C63: CLIENT PAYMENT | E63: 9412 | F63: 103933 | H63: =IF(ISNA(VLOOKUP(B63,Cash_Book!B:D,2,FALSE)),"Missing","Found") -> Found
A64: 03-04-2026 | B64: TXN1062 | C64: NEFT CREDIT | E64: 5557 | F64: 109490 | H64: =IF(ISNA(VLOOKUP(B64,Cash_Book!B:D,2,FALSE)),"Missing","Found") -> Found
A65: 04-04-2026 | B65: TXN1063 | C65: ATM WITHDRAWAL | D65: 7443 | F65: 102047 | H65: =IF(ISNA(VLOOKUP(B65,Cash_Book!B:D,2,FALSE)),"Missing","Found") -> Found
A66: 05-04-2026 | B66: TXN1064 | C66: BANK FEES | D66: 643 | F66: 101404 | H66: =IF(ISNA(VLOOKUP(B66,Cash_Book!B:D,2,FALSE)),"Missing","Found") -> Found
A67: 06-04-2026 | B67: TXN1065 | C67: UPI RECEIPT | E67: 2139 | F67: 103543 | H67: =IF(ISNA(VLOOKUP(B67,Cash_Book!B:D,2,FALSE)),"Missing","Found") -> Found
A68: 07-04-2026 | B68: TXN1066 | C68: NEFT CREDIT | E68: 2249 | F68: 105792 | H68: =IF(ISNA(VLOOKUP(B68,Cash_Book!B:D,2,FALSE)),"Missing","Found") -> Found
A69: 08-04-2026 | B69: TXN1067 | C69: NEFT CREDIT | E69: 8692 | F69: 114484 | H69: =IF(ISNA(VLOOKUP(B69,Cash_Book!B:D,2,FALSE)),"Missing","Found") -> Found
A70: 09-04-2026 | B70: TXN1068 | C70: ATM WITHDRAWAL | D70: 2316 | F70: 112168 | H70: =IF(ISNA(VLOOKUP(B70,Cash_Book!B:D,2,FALSE)),"Missing","Found") -> Found
A71: 10-04-2026 | B71: TXN1069 | C71: EFT PAYMENT | D71: 1884 | F71: 110284 | H71: =IF(ISNA(VLOOKUP(B71,Cash_Book!B:D,2,FALSE)),"Missing","Found") -> Found
A72: 11-04-2026 | B72: TXN1070 | C72: NEFT CREDIT | E72: 816 | F72: 111100 | H72: =IF(ISNA(VLOOKUP(B72,Cash_Book!B:D,2,FALSE)),"Missing","Found") -> Found
A73: 12-04-2026 | B73: TXN1071 | C73: CHEQUE PAYMENT | D73: 4082 | F73: 107018 | H73: =IF(ISNA(VLOOKUP(B73,Cash_Book!B:D,2,FALSE)),"Missing","Found") -> Found
A74: 13-04-2026 | B74: TXN1072 | C74: UPI RECEIPT | E74: 7808 | F74: 114826 | H74: =IF(ISNA(VLOOKUP(B74,Cash_Book!B:D,2,FALSE)),"Missing","Found") -> Found
A75: 14-04-2026 | B75: TXN1073 | C75: UPI RECEIPT | E75: 7180 | F75: 122006 | H75: =IF(ISNA(VLOOKUP(B75,Cash_Book!B:D,2,FALSE)),"Missing","Found") -> Found
A76: 15-04-2026 | B76: TXN1074 | C76: CHEQUE PAYMENT | D76: 5295 | F76: 116711 | H76: =IF(ISNA(VLOOKUP(B76,Cash_Book!B:D,2,FALSE)),"Missing","Found") -> Found
A77: 16-04-2026 | B77: TXN1075 | C77: NEFT CREDIT | E77: 5377 | F77: 122088 | H77: =IF(ISNA(VLOOKUP(B77,Cash_Book!B:D,2,FALSE)),"Missing","Found") -> Missing
A78: 17-04-2026 | B78: TXN1076 | C78: CLIENT PAYMENT | E78: 8745 | F78: 130833 | H78: =IF(ISNA(VLOOKUP(B78,Cash_Book!B:D,2,FALSE)),"Missing","Found") -> Found
A79: 18-04-2026 | B79: TXN1077 | C79: ATM WITHDRAWAL | D79: 561 | F79: 130272 | H79: =IF(ISNA(VLOOKUP(B79,Cash_Book!B:D,2,FALSE)),"Missing","Found") -> Found
A80: 19-04-2026 | B80: TXN1078 | C80: BANK FEES | D80: 5575 | F80: 124697 | H80: =IF(ISNA(VLOOKUP(B80,Cash_Book!B:D,2,FALSE)),"Missing","Found") -> Found
A81: 20-04-2026 | B81: TXN1079 | C81: UPI RECEIPT | E81: 918 | F81: 125615 | H81: =IF(ISNA(VLOOKUP(B81,Cash_Book!B:D,2,FALSE)),"Missing","Found") -> Found
A82: 21-04-2026 | B82: TXN1080 | C82: UTILITY BILL | D82: 1055 | F82: 124560 | H82: =IF(ISNA(VLOOKUP(B82,Cash_Book!B:D,2,FALSE)),"Missing","Found") -> Found
A83: 22-04-2026 | B83: TXN1081 | C83: UPI RECEIPT | E83: 1665 | F83: 126225 | H83: =IF(ISNA(VLOOKUP(B83,Cash_Book!B:D,2,FALSE)),"Missing","Found") -> Found
A84: 23-04-2026 | B84: TXN1082 | C84: SALARY CREDIT | E84: 9334 | F84: 135559 | H84: =IF(ISNA(VLOOKUP(B84,Cash_Book!B:D,2,FALSE)),"Missing","Found") -> Missing
A85: 24-04-2026 | B85: TXN1083 | C85: ATM WITHDRAWAL | D85: 3126 | F85: 132433 | H85: =IF(ISNA(VLOOKUP(B85,Cash_Book!B:D,2,FALSE)),"Missing","Found") -> Found
A86: 25-04-2026 | B86: TXN1084 | C86: CHEQUE PAYMENT | D86: 701 | F86: 131732 | H86: =IF(ISNA(VLOOKUP(B86,Cash_Book!B:D,2,FALSE)),"Missing","Found") -> Found
A87: 26-04-2026 | B87: TXN1085 | C87: BANK FEES | D87: 6151 | F87: 125581 | H87: =IF(ISNA(VLOOKUP(B87,Cash_Book!B:D,2,FALSE)),"Missing","Found") -> Found
A88: 27-04-2026 | B88: TXN1086 | C88: UPI RECEIPT | E88: 4690 | F88: 130271 | H88: =IF(ISNA(VLOOKUP(B88,Cash_Book!B:D,2,FALSE)),"Missing","Found") -> Found
A89: 28-04-2026 | B89: TXN1087 | C89: EFT PAYMENT | D89: 992 | F89: 129279 | H89: =IF(ISNA(VLOOKUP(B89,Cash_Book!B:D,2,FALSE)),"Missing","Found") -> Found
A90: 29-04-2026 | B90: TXN1088 | C90: SALARY CREDIT | E90: 6022 | F90: 135301 | H90: =IF(ISNA(VLOOKUP(B90,Cash_Book!B:D,2,FALSE)),"Missing","Found") -> Found
A91: 30-04-2026 | B91: TXN1089 | C91: NEFT CREDIT | E91: 5013 | F91: 140314 | H91: =IF(ISNA(VLOOKUP(B91,Cash_Book!B:D,2,FALSE)),"Missing","Found") -> Found
A92: 01-04-2026 | B92: TXN1090 | C92: UPI RECEIPT | E92: 9274 | F92: 149588 | H92: =IF(ISNA(VLOOKUP(B92,Cash_Book!B:D,2,FALSE)),"Missing","Found") -> Missing
A93: 02-04-2026 | B93: TXN1091 | C93: EFT RECEIPT | E93: 8977 | F93: 158565 | H93: =IF(ISNA(VLOOKUP(B93,Cash_Book!B:D,2,FALSE)),"Missing","Found") -> Found
A94: 03-04-2026 | B94: TXN1092 | C94: SALARY CREDIT | E94: 3211 | F94: 161776 | H94: =IF(ISNA(VLOOKUP(B94,Cash_Book!B:D,2,FALSE)),"Missing","Found") -> Found
A95: 04-04-2026 | B95: TXN1093 | C95: BANK FEES | D95: 993 | F95: 160783 | H95: =IF(ISNA(VLOOKUP(B95,Cash_Book!B:D,2,FALSE)),"Missing","Found") -> Found
A96: 05-04-2026 | B96: TXN1094 | C96: CHEQUE PAYMENT | D96: 6193 | F96: 154590 | H96: =IF(ISNA(VLOOKUP(B96,Cash_Book!B:D,2,FALSE)),"Missing","Found") -> Found
A97: 06-04-2026 | B97: TXN1095 | C97: UTILITY BILL | D97: 7225 | F97: 147365 | H97: =IF(ISNA(VLOOKUP(B97,Cash_Book!B:D,2,FALSE)),"Missing","Found") -> Found
A98: 07-04-2026 | B98: TXN1096 | C98: UTILITY BILL | D98: 7022 | F98: 140343 | H98: =IF(ISNA(VLOOKUP(B98,Cash_Book!B:D,2,FALSE)),"Missing","Found") -> Found
A99: 08-04-2026 | B99: TXN1097 | C99: CLIENT PAYMENT | E99: 3312 | F99: 143655 | H99: =IF(ISNA(VLOOKUP(B99,Cash_Book!B:D,2,FALSE)),"Missing","Found") -> Found
A100: 09-04-2026 | B100: TXN1098 | C100: NEFT CREDIT | E100: 8306 | F100: 151961 | H100: =IF(ISNA(VLOOKUP(B100,Cash_Book!B:D,2,FALSE)),"Missing","Found") -> Found
...

Sheet Dashboard
A3: Row Labels | B3: Sum of Debit | C3: Sum of Credit
A4: ATM WITHDRAWAL | B4: 34982
A5: BANK FEES | B5: 40386
A6: CHEQUE PAYMENT | B6: 31886
A7: CLIENT PAYMENT | C7: 45490
A8: EFT PAYMENT | B8: 29824
A9: EFT RECEIPT | C9: 46729
A10: NEFT CREDIT | C10: 61940
A11: SALARY CREDIT | C11: 63612
A12: UPI RECEIPT | C12: 33422
A13: UTILITY BILL | B13: 34415
A14: Grand Total | B14: 171493 | C14: 251193

Sheet Summary
A1: Metric | B1: Formula
A2: Total Transactions | B2: =COUNTA(Cash_Book!B:B)-1 -> 93
A3: Missing Transactions | B3: =COUNTIF(Bank_Statement!H:H,"Missing") -> 8
A4: Mismatched Transactions | B4: =COUNTIF(Cash_Book!G:G,"Mismatch") -> 5
A5: Duplicate Transactions | B5: =COUNTIF(Cash_Book!I:I,">1") -> 2
A6: Total Debit | B6: =SUM(Cash_Book!D:D) -> 171493
A7: Total Credit | B7: =SUM(Cash_Book!E:E) -> 251193

Sheet Cash_Book
A1: Date | B1: Transaction_ID | C1: Description | D1: Debit | E1: Credit | F1: Balance | G1: Amount Check | H1: Bank Balance Lookup | I1: Duplicate Check
A2: 02-04-2026 | B2: TXN1001 | C2: CLIENT PAYMENT | E2: 9769 | F2: 55816 | G2: =IF(OR(D2<>VLOOKUP(B2,Bank_Statement!B:F,3,FALSE),E2<>VLOOKUP(B2,Bank_Statement!B:F,4,FALSE)),"Mismatch","Match") -> Match | H2: =_xlfn.XLOOKUP(B2,Bank_Statement!B2:B101,Bank_Statement!F2:F101,"Not Found") -> 55816 | I2: =COUNTIF(B:B,B2) -> 1
A3: 03-04-2026 | B3: TXN1002 | C3: EFT PAYMENT | D3: 4142 | F3: 51674 | G3: =IF(OR(D3<>VLOOKUP(B3,Bank_Statement!B:F,3,FALSE),E3<>VLOOKUP(B3,Bank_Statement!B:F,4,FALSE)),"Mismatch","Match") -> Match | H3: =_xlfn.XLOOKUP(B3,Bank_Statement!B3:B102,Bank_Statement!F3:F102,"Not Found") -> 51674 | I3: =COUNTIF(B:B,B3) -> 1
A4: 04-04-2026 | B4: TXN1003 | C4: EFT RECEIPT | E4: 4282 | F4: 55956 | G4: =IF(OR(D4<>VLOOKUP(B4,Bank_Statement!B:F,3,FALSE),E4<>VLOOKUP(B4,Bank_Statement!B:F,4,FALSE)),"Mismatch","Match") -> Match | H4: =_xlfn.XLOOKUP(B4,Bank_Statement!B4:B103,Bank_Statement!F4:F103,"Not Found") -> 55956 | I4: =COUNTIF(B:B,B4) -> 1
A5: 05-04-2026 | B5: TXN1004 | C5: SALARY CREDIT | E5: 8715 | F5: 64671 | G5: =IF(OR(D5<>VLOOKUP(B5,Bank_Statement!B:F,3,FALSE),E5<>VLOOKUP(B5,Bank_Statement!B:F,4,FALSE)),"Mismatch","Match") -> Match | H5: =_xlfn.XLOOKUP(B5,Bank_Statement!B5:B104,Bank_Statement!F5:F104,"Not Found") -> 64671 | I5: =COUNTIF(B:B,B5) -> 1
A6: 06-04-2026 | B6: TXN1005 | C6: UPI RECEIPT | E6: 7433 | F6: 72104 | G6: =IF(OR(D6<>VLOOKUP(B6,Bank_Statement!B:F,3,FALSE),E6<>VLOOKUP(B6,Bank_Statement!B:F,4,FALSE)),"Mismatch","Match") -> Match | H6: =_xlfn.XLOOKUP(B6,Bank_Statement!B6:B105,Bank_Statement!F6:F105,"Not Found") -> 72104 | I6: =COUNTIF(B:B,B6) -> 1
A7: 07-04-2026 | B7: TXN1006 | C7: ATM WITHDRAWAL | D7: 4347 | F7: 67757 | G7: =IF(OR(D7<>VLOOKUP(B7,Bank_Statement!B:F,3,FALSE),E7<>VLOOKUP(B7,Bank_Statement!B:F,4,FALSE)),"Mismatch","Match") -> Match | H7: =_xlfn.XLOOKUP(B7,Bank_Statement!B7:B106,Bank_Statement!F7:F106,"Not Found") -> 67757 | I7: =COUNTIF(B:B,B7) -> 1
A8: 08-04-2026 | B8: TXN1007 | C8: BANK FEES | D8: 4463 | F8: 63294 | G8: =IF(OR(D8<>VLOOKUP(B8,Bank_Statement!B:F,3,FALSE),E8<>VLOOKUP(B8,Bank_Statement!B:F,4,FALSE)),"Mismatch","Match") -> Match | H8: =_xlfn.XLOOKUP(B8,Bank_Statement!B8:B107,Bank_Statement!F8:F107,"Not Found") -> 63294 | I8: =COUNTIF(B:B,B8) -> 1
A9: 09-04-2026 | B9: TXN1008 | C9: NEFT CREDIT | E9: 7717 | F9: 71011 | G9: =IF(OR(D9<>VLOOKUP(B9,Bank_Statement!B:F,3,FALSE),E9<>VLOOKUP(B9,Bank_Statement!B:F,4,FALSE)),"Mismatch","Match") -> Match | H9: =_xlfn.XLOOKUP(B9,Bank_Statement!B9:B108,Bank_Statement!F9:F108,"Not Found") -> 71011 | I9: =COUNTIF(B:B,B9) -> 1
A10: 10-04-2026 | B10: TXN1009 | C10: NEFT CREDIT | E10: 4562 | F10: 75573 | G10: =IF(OR(D10<>VLOOKUP(B10,Bank_Statement!B:F,3,FALSE),E10<>VLOOKUP(B10,Bank_Statement!B:F,4,FALSE)),"Mismatch","Match") -> Match | H10: =_xlfn.XLOOKUP(B10,Bank_Statement!B10:B109,Bank_Statement!F10:F109,"Not Found") -> 75573 | I10: =COUNTIF(B:B,B10) -> 1
A11: 11-04-2026 | B11: TXN1010 | C11: SALARY CREDIT | E11: 3826 | F11: 79399 | G11: =IF(OR(D11<>VLOOKUP(B11,Bank_Statement!B:F,3,FALSE),E11<>VLOOKUP(B11,Bank_Statement!B:F,4,FALSE)),"Mismatch","Match") -> Match | H11: =_xlfn.XLOOKUP(B11,Bank_Statement!B11:B110,Bank_Statement!F11:F110,"Not Found") -> 79399 | I11: =COUNTIF(B:B,B11) -> 1
A12: 12-04-2026 | B12: TXN1011 | C12: EFT PAYMENT | D12: 6010 | F12: 73389 | G12: =IF(OR(D12<>VLOOKUP(B12,Bank_Statement!B:F,3,FALSE),E12<>VLOOKUP(B12,Bank_Statement!B:F,4,FALSE)),"Mismatch","Match") -> Match | H12: =_xlfn.XLOOKUP(B12,Bank_Statement!B12:B111,Bank_Statement!F12:F111,"Not Found") -> 73389 | I12: =COUNTIF(B:B,B12) -> 1
A13: 13-04-2026 | B13: TXN1012 | C13: NEFT CREDIT | E13: 1679 | F13: 75068 | G13: =IF(OR(D13<>VLOOKUP(B13,Bank_Statement!B:F,3,FALSE),E13<>VLOOKUP(B13,Bank_Statement!B:F,4,FALSE)),"Mismatch","Match") -> Match | H13: =_xlfn.XLOOKUP(B13,Bank_Statement!B13:B112,Bank_Statement!F13:F112,"Not Found") -> 75068 | I13: =COUNTIF(B:B,B13) -> 1
A14: 14-04-2026 | B14: TXN1013 | C14: BANK FEES | D14: 738 | F14: 74330 | G14: =IF(OR(D14<>VLOOKUP(B14,Bank_Statement!B:F,3,FALSE),E14<>VLOOKUP(B14,Bank_Statement!B:F,4,FALSE)),"Mismatch","Match") -> Match | H14: =_xlfn.XLOOKUP(B14,Bank_Statement!B14:B113,Bank_Statement!F14:F113,"Not Found") -> 74330 | I14: =COUNTIF(B:B,B14) -> 1
A15: 15-04-2026 | B15: TXN1014 | C15: BANK FEES | D15: 726 | F15: 73604 | G15: =IF(OR(D15<>VLOOKUP(B15,Bank_Statement!B:F,3,FALSE),E15<>VLOOKUP(B15,Bank_Statement!B:F,4,FALSE)),"Mismatch","Match") -> Match | H15: =_xlfn.XLOOKUP(B15,Bank_Statement!B15:B114,Bank_Statement!F15:F114,"Not Found") -> 73604 | I15: =COUNTIF(B:B,B15) -> 1
A16: 17-04-2026 | B16: TXN1016 | C16: ATM WITHDRAWAL | D16: 327 | F16: 77538 | G16: =IF(OR(D16<>VLOOKUP(B16,Bank_Statement!B:F,3,FALSE),E16<>VLOOKUP(B16,Bank_Statement!B:F,4,FALSE)),"Mismatch","Match") -> Match | H16: =_xlfn.XLOOKUP(B16,Bank_Statement!B16:B115,Bank_Statement!F16:F115,"Not Found") -> 77538 | I16: =COUNTIF(B:B,B16) -> 1
A17: 18-04-2026 | B17: TXN1017 | C17: SALARY CREDIT | E17: 9248 | F17: 86786 | G17: =IF(OR(D17<>VLOOKUP(B17,Bank_Statement!B:F,3,FALSE),E17<>VLOOKUP(B17,Bank_Statement!B:F,4,FALSE)),"Mismatch","Match") -> Match | H17: =_xlfn.XLOOKUP(B17,Bank_Statement!B17:B116,Bank_Statement!F17:F116,"Not Found") -> 86786 | I17: =COUNTIF(B:B,B17) -> 1
A18: 19-04-2026 | B18: TXN1018 | C18: NEFT CREDIT | E18: 1725 | F18: 88536 | G18: =IF(OR(D18<>VLOOKUP(B18,Bank_Statement!B:F,3,FALSE),E18<>VLOOKUP(B18,Bank_Statement!B:F,4,FALSE)),"Mismatch","Match") -> Mismatch | H18: =_xlfn.XLOOKUP(B18,Bank_Statement!B18:B117,Bank_Statement!F18:F117,"Not Found") -> 88536 | I18: =COUNTIF(B:B,B18) -> 1
A19: 20-04-2026 | B19: TXN1019 | C19: EFT RECEIPT | E19: 4600 | F19: 93136 | G19: =IF(OR(D19<>VLOOKUP(B19,Bank_Statement!B:F,3,FALSE),E19<>VLOOKUP(B19,Bank_Statement!B:F,4,FALSE)),"Mismatch","Match") -> Match | H19: =_xlfn.XLOOKUP(B19,Bank_Statement!B19:B118,Bank_Statement!F19:F118,"Not Found") -> 93136 | I19: =COUNTIF(B:B,B19) -> 1
A20: 21-04-2026 | B20: TXN1020 | C20: CLIENT PAYMENT | E20: 4978 | F20: 98114 | G20: =IF(OR(D20<>VLOOKUP(B20,Bank_Statement!B:F,3,FALSE),E20<>VLOOKUP(B20,Bank_Statement!B:F,4,FALSE)),"Mismatch","Match") -> Match | H20: =_xlfn.XLOOKUP(B20,Bank_Statement!B20:B119,Bank_Statement!F20:F119,"Not Found") -> 98114 | I20: =COUNTIF(B:B,B20) -> 1
A21: 22-04-2026 | B21: TXN1021 | C21: EFT PAYMENT | D21: 5630 | F21: 92484 | G21: =IF(OR(D21<>VLOOKUP(B21,Bank_Statement!B:F,3,FALSE),E21<>VLOOKUP(B21,Bank_Statement!B:F,4,FALSE)),"Mismatch","Match") -> Match | H21: =_xlfn.XLOOKUP(B21,Bank_Statement!B21:B120,Bank_Statement!F21:F120,"Not Found") -> 92484 | I21: =COUNTIF(B:B,B21) -> 1
A22: 23-04-2026 | B22: TXN1022 | C22: CHEQUE PAYMENT | D22: 3885 | F22: 88599 | G22: =IF(OR(D22<>VLOOKUP(B22,Bank_Statement!B:F,3,FALSE),E22<>VLOOKUP(B22,Bank_Statement!B:F,4,FALSE)),"Mismatch","Match") -> Match | H22: =_xlfn.XLOOKUP(B22,Bank_Statement!B22:B121,Bank_Statement!F22:F121,"Not Found") -> 88599 | I22: =COUNTIF(B:B,B22) -> 1
A23: 24-04-2026 | B23: TXN1023 | C23: BANK FEES | D23: 4845 | F23: 83754 | G23: =IF(OR(D23<>VLOOKUP(B23,Bank_Statement!B:F,3,FALSE),E23<>VLOOKUP(B23,Bank_Statement!B:F,4,FALSE)),"Mismatch","Match") -> Match | H23: =_xlfn.XLOOKUP(B23,Bank_Statement!B23:B122,Bank_Statement!F23:F122,"Not Found") -> 83754 | I23: =COUNTIF(B:B,B23) -> 1
A24: 25-04-2026 | B24: TXN1024 | C24: NEFT CREDIT | E24: 5343 | F24: 89097 | G24: =IF(OR(D24<>VLOOKUP(B24,Bank_Statement!B:F,3,FALSE),E24<>VLOOKUP(B24,Bank_Statement!B:F,4,FALSE)),"Mismatch","Match") -> Match | H24: =_xlfn.XLOOKUP(B24,Bank_Statement!B24:B123,Bank_Statement!F24:F123,"Not Found") -> 89097 | I24: =COUNTIF(B:B,B24) -> 1
A25: 26-04-2026 | B25: TXN1025 | C25: ATM WITHDRAWAL | D25: 5245 | F25: 83852 | G25: =IF(OR(D25<>VLOOKUP(B25,Bank_Statement!B:F,3,FALSE),E25<>VLOOKUP(B25,Bank_Statement!B:F,4,FALSE)),"Mismatch","Match") -> Match | H25: =_xlfn.XLOOKUP(B25,Bank_Statement!B25:B124,Bank_Statement!F25:F124,"Not Found") -> 83852 | I25: =COUNTIF(B:B,B25) -> 1
A26: 27-04-2026 | B26: TXN1026 | C26: SALARY CREDIT | E26: 1936 | F26: 85788 | G26: =IF(OR(D26<>VLOOKUP(B26,Bank_Statement!B:F,3,FALSE),E26<>VLOOKUP(B26,Bank_Statement!B:F,4,FALSE)),"Mismatch","Match") -> Match | H26: =_xlfn.XLOOKUP(B26,Bank_Statement!B26:B125,Bank_Statement!F26:F125,"Not Found") -> 85788 | I26: =COUNTIF(B:B,B26) -> 1
A27: 28-04-2026 | B27: TXN1027 | C27: SALARY CREDIT | E27: 8843 | F27: 94631 | G27: =IF(OR(D27<>VLOOKUP(B27,Bank_Statement!B:F,3,FALSE),E27<>VLOOKUP(B27,Bank_Statement!B:F,4,FALSE)),"Mismatch","Match") -> Match | H27: =_xlfn.XLOOKUP(B27,Bank_Statement!B27:B126,Bank_Statement!F27:F126,"Not Found") -> 94631 | I27: =COUNTIF(B:B,B27) -> 1
A28: 29-04-2026 | B28: TXN1028 | C28: UTILITY BILL | D28: 4804 | F28: 89827 | G28: =IF(OR(D28<>VLOOKUP(B28,Bank_Statement!B:F,3,FALSE),E28<>VLOOKUP(B28,Bank_Statement!B:F,4,FALSE)),"Mismatch","Match") -> Match | H28: =_xlfn.XLOOKUP(B28,Bank_Statement!B28:B127,Bank_Statement!F28:F127,"Not Found") -> 89827 | I28: =COUNTIF(B:B,B28) -> 1
A29: 30-04-2026 | B29: TXN1029 | C29: UPI RECEIPT | E29: 570 | F29: 90397 | G29: =IF(OR(D29<>VLOOKUP(B29,Bank_Statement!B:F,3,FALSE),E29<>VLOOKUP(B29,Bank_Statement!B:F,4,FALSE)),"Mismatch","Match") -> Match | H29: =_xlfn.XLOOKUP(B29,Bank_Statement!B29:B128,Bank_Statement!F29:F128,"Not Found") -> 90397 | I29: =COUNTIF(B:B,B29) -> 1
A30: 02-04-2026 | B30: TXN1031 | C30: ATM WITHDRAWAL | D30: 4087 | F30: 94246 | G30: =IF(OR(D30<>VLOOKUP(B30,Bank_Statement!B:F,3,FALSE),E30<>VLOOKUP(B30,Bank_Statement!B:F,4,FALSE)),"Mismatch","Match") -> Match | H30: =_xlfn.XLOOKUP(B30,Bank_Statement!B30:B129,Bank_Statement!F30:F129,"Not Found") -> 94246 | I30: =COUNTIF(B:B,B30) -> 1
A31: 03-04-2026 | B31: TXN1032 | C31: EFT RECEIPT | E31: 5948 | F31: 100194 | G31: =IF(OR(D31<>VLOOKUP(B31,Bank_Statement!B:F,3,FALSE),E31<>VLOOKUP(B31,Bank_Statement!B:F,4,FALSE)),"Mismatch","Match") -> Match | H31: =_xlfn.XLOOKUP(B31,Bank_Statement!B31:B130,Bank_Statement!F31:F130,"Not Found") -> 100194 | I31: =COUNTIF(B:B,B31) -> 1
A32: 04-04-2026 | B32: TXN1033 | C32: NEFT CREDIT | E32: 1423 | F32: 101617 | G32: =IF(OR(D32<>VLOOKUP(B32,Bank_Statement!B:F,3,FALSE),E32<>VLOOKUP(B32,Bank_Statement!B:F,4,FALSE)),"Mismatch","Match") -> Match | H32: =_xlfn.XLOOKUP(B32,Bank_Statement!B32:B131,Bank_Statement!F32:F131,"Not Found") -> 101617 | I32: =COUNTIF(B:B,B32) -> 1
A33: 05-04-2026 | B33: TXN1034 | C33: SALARY CREDIT | E33: 1766 | F33: 103383 | G33: =IF(OR(D33<>VLOOKUP(B33,Bank_Statement!B:F,3,FALSE),E33<>VLOOKUP(B33,Bank_Statement!B:F,4,FALSE)),"Mismatch","Match") -> Match | H33: =_xlfn.XLOOKUP(B33,Bank_Statement!B33:B132,Bank_Statement!F33:F132,"Not Found") -> 103383 | I33: =COUNTIF(B:B,B33) -> 1
A34: 06-04-2026 | B34: TXN1035 | C34: EFT PAYMENT | D34: 7757 | F34: 95626 | G34: =IF(OR(D34<>VLOOKUP(B34,Bank_Statement!B:F,3,FALSE),E34<>VLOOKUP(B34,Bank_Statement!B:F,4,FALSE)),"Mismatch","Match") -> Match | H34: =_xlfn.XLOOKUP(B34,Bank_Statement!B34:B133,Bank_Statement!F34:F133,"Not Found") -> 95626 | I34: =COUNTIF(B:B,B34) -> 1
A35: 07-04-2026 | B35: TXN1036 | C35: BANK FEES | D35: 3449 | F35: 92177 | G35: =IF(OR(D35<>VLOOKUP(B35,Bank_Statement!B:F,3,FALSE),E35<>VLOOKUP(B35,Bank_Statement!B:F,4,FALSE)),"Mismatch","Match") -> Match | H35: =_xlfn.XLOOKUP(B35,Bank_Statement!B35:B134,Bank_Statement!F35:F134,"Not Found") -> 92177 | I35: =COUNTIF(B:B,B35) -> 1
A36: 08-04-2026 | B36: TXN1037 | C36: CHEQUE PAYMENT | D36: 2936 | F36: 89241 | G36: =IF(OR(D36<>VLOOKUP(B36,Bank_Statement!B:F,3,FALSE),E36<>VLOOKUP(B36,Bank_Statement!B:F,4,FALSE)),"Mismatch","Match") -> Match | H36: =_xlfn.XLOOKUP(B36,Bank_Statement!B36:B135,Bank_Statement!F36:F135,"Not Found") -> 89241 | I36: =COUNTIF(B:B,B36) -> 1
A37: 09-04-2026 | B37: TXN1038 | C37: ATM WITHDRAWAL | D37: 7530 | F37: 81711 | G37: =IF(OR(D37<>VLOOKUP(B37,Bank_Statement!B:F,3,FALSE),E37<>VLOOKUP(B37,Bank_Statement!B:F,4,FALSE)),"Mismatch","Match") -> Match | H37: =_xlfn.XLOOKUP(B37,Bank_Statement!B37:B136,Bank_Statement!F37:F136,"Not Found") -> 81711 | I37: =COUNTIF(B:B,B37) -> 1
A38: 10-04-2026 | B38: TXN1039 | C38: SALARY CREDIT | E38: 6404 | F38: 88115 | G38: =IF(OR(D38<>VLOOKUP(B38,Bank_Statement!B:F,3,FALSE),E38<>VLOOKUP(B38,Bank_Statement!B:F,4,FALSE)),"Mismatch","Match") -> Match | H38: =_xlfn.XLOOKUP(B38,Bank_Statement!B38:B137,Bank_Statement!F38:F137,"Not Found") -> 88115 | I38: =COUNTIF(B:B,B38) -> 1
A39: 11-04-2026 | B39: TXN1040 | C39: UTILITY BILL | D39: 4195 | F39: 83970 | G39: =IF(OR(D39<>VLOOKUP(B39,Bank_Statement!B:F,3,FALSE),E39<>VLOOKUP(B39,Bank_Statement!B:F,4,FALSE)),"Mismatch","Match") -> Mismatch | H39: =_xlfn.XLOOKUP(B39,Bank_Statement!B39:B138,Bank_Statement!F39:F138,"Not Found") -> 83970 | I39: =COUNTIF(B:B,B39) -> 1
A40: 12-04-2026 | B40: TXN1041 | C40: CLIENT PAYMENT | E40: 9274 | F40: 93244 | G40: =IF(OR(D40<>VLOOKUP(B40,Bank_Statement!B:F,3,FALSE),E40<>VLOOKUP(B40,Bank_Statement!B:F,4,FALSE)),"Mismatch","Match") -> Match | H40: =_xlfn.XLOOKUP(B40,Bank_Statement!B40:B139,Bank_Statement!F40:F139,"Not Found") -> 93244 | I40: =COUNTIF(B:B,B40) -> 1
A41: 13-04-2026 | B41: TXN1042 | C41: BANK FEES | D41: 684 | F41: 92560 | G41: =IF(OR(D41<>VLOOKUP(B41,Bank_Statement!B:F,3,FALSE),E41<>VLOOKUP(B41,Bank_Statement!B:F,4,FALSE)),"Mismatch","Match") -> Match | H41: =_xlfn.XLOOKUP(B41,Bank_Statement!B41:B140,Bank_Statement!F41:F140,"Not Found") -> 92560 | I41: =COUNTIF(B:B,B41) -> 1
A42: 14-04-2026 | B42: TXN1043 | C42: SALARY CREDIT | E42: 4307 | F42: 96867 | G42: =IF(OR(D42<>VLOOKUP(B42,Bank_Statement!B:F,3,FALSE),E42<>VLOOKUP(B42,Bank_Statement!B:F,4,FALSE)),"Mismatch","Match") -> Match | H42: =_xlfn.XLOOKUP(B42,Bank_Statement!B42:B141,Bank_Statement!F42:F141,"Not Found") -> 96867 | I42: =COUNTIF(B:B,B42) -> 1
A43: 15-04-2026 | B43: TXN1044 | C43: NEFT CREDIT | E43: 2549 | F43: 99416 | G43: =IF(OR(D43<>VLOOKUP(B43,Bank_Statement!B:F,3,FALSE),E43<>VLOOKUP(B43,Bank_Statement!B:F,4,FALSE)),"Mismatch","Match") -> Match | H43: =_xlfn.XLOOKUP(B43,Bank_Statement!B43:B142,Bank_Statement!F43:F142,"Not Found") -> 99416 | I43: =COUNTIF(B:B,B43) -> 1
A44: 17-04-2026 | B44: TXN1046 | C44: BANK FEES | D44: 4296 | F44: 93189 | G44: =IF(OR(D44<>VLOOKUP(B44,Bank_Statement!B:F,3,FALSE),E44<>VLOOKUP(B44,Bank_Statement!B:F,4,FALSE)),"Mismatch","Match") -> Match | H44: =_xlfn.XLOOKUP(B44,Bank_Statement!B44:B143,Bank_Statement!F44:F143,"Not Found") -> 93189 | I44: =COUNTIF(B:B,B44) -> 1
A45: 18-04-2026 | B45: TXN1047 | C45: CHEQUE PAYMENT | D45: 2986 | F45: 90203 | G45: =IF(OR(D45<>VLOOKUP(B45,Bank_Statement!B:F,3,FALSE),E45<>VLOOKUP(B45,Bank_Statement!B:F,4,FALSE)),"Mismatch","Match") -> Match | H45: =_xlfn.XLOOKUP(B45,Bank_Statement!B45:B144,Bank_Statement!F45:F144,"Not Found") -> 90203 | I45: =COUNTIF(B:B,B45) -> 1
A46: 19-04-2026 | B46: TXN1048 | C46: EFT RECEIPT | E46: 7153 | F46: 97356 | G46: =IF(OR(D46<>VLOOKUP(B46,Bank_Statement!B:F,3,FALSE),E46<>VLOOKUP(B46,Bank_Statement!B:F,4,FALSE)),"Mismatch","Match") -> Match | H46: =_xlfn.XLOOKUP(B46,Bank_Statement!B46:B145,Bank_Statement!F46:F145,"Not Found") -> 97356 | I46: =COUNTIF(B:B,B46) -> 1
A47: 20-04-2026 | B47: TXN1049 | C47: NEFT CREDIT | E47: 2656 | F47: 100012 | G47: =IF(OR(D47<>VLOOKUP(B47,Bank_Statement!B:F,3,FALSE),E47<>VLOOKUP(B47,Bank_Statement!B:F,4,FALSE)),"Mismatch","Match") -> Match | H47: =_xlfn.XLOOKUP(B47,Bank_Statement!B47:B146,Bank_Statement!F47:F146,"Not Found") -> 100012 | I47: =COUNTIF(B:B,B47) -> 1
A48: 21-04-2026 | B48: TXN1050 | C48: BANK FEES | D48: 7823 | F48: 92189 | G48: =IF(OR(D48<>VLOOKUP(B48,Bank_Statement!B:F,3,FALSE),E48<>VLOOKUP(B48,Bank_Statement!B:F,4,FALSE)),"Mismatch","Match") -> Match | H48: =_xlfn.XLOOKUP(B48,Bank_Statement!B48:B147,Bank_Statement!F48:F147,"Not Found") -> 92189 | I48: =COUNTIF(B:B,B48) -> 1
A49: 22-04-2026 | B49: TXN1051 | C49: UPI RECEIPT | E49: 1044 | F49: 93233 | G49: =IF(OR(D49<>VLOOKUP(B49,Bank_Statement!B:F,3,FALSE),E49<>VLOOKUP(B49,Bank_Statement!B:F,4,FALSE)),"Mismatch","Match") -> Match | H49: =_xlfn.XLOOKUP(B49,Bank_Statement!B49:B148,Bank_Statement!F49:F148,"Not Found") -> 93233 | I49: =COUNTIF(B:B,B49) -> 1
A50: 23-04-2026 | B50: TXN1052 | C50: UTILITY BILL | D50: 4878 | F50: 88355 | G50: =IF(OR(D50<>VLOOKUP(B50,Bank_Statement!B:F,3,FALSE),E50<>VLOOKUP(B50,Bank_Statement!B:F,4,FALSE)),"Mismatch","Match") -> Match | H50: =_xlfn.XLOOKUP(B50,Bank_Statement!B50:B149,Bank_Statement!F50:F149,"Not Found") -> 88355 | I50: =COUNTIF(B:B,B50) -> 1
A51: 24-04-2026 | B51: TXN1053 | C51: UTILITY BILL | D51: 2999 | F51: 85356 | G51: =IF(OR(D51<>VLOOKUP(B51,Bank_Statement!B:F,3,FALSE),E51<>VLOOKUP(B51,Bank_Statement!B:F,4,FALSE)),"Mismatch","Match") -> Match | H51: =_xlfn.XLOOKUP(B51,Bank_Statement!B51:B150,Bank_Statement!F51:F150,"Not Found") -> 85356 | I51: =COUNTIF(B:B,B51) -> 1
A52: 25-04-2026 | B52: TXN1054 | C52: EFT PAYMENT | D52: 3409 | F52: 81947 | G52: =IF(OR(D52<>VLOOKUP(B52,Bank_Statement!B:F,3,FALSE),E52<>VLOOKUP(B52,Bank_Statement!B:F,4,FALSE)),"Mismatch","Match") -> Match | H52: =_xlfn.XLOOKUP(B52,Bank_Statement!B52:B151,Bank_Statement!F52:F151,"Not Found") -> 81947 | I52: =COUNTIF(B:B,B52) -> 1
A53: 26-04-2026 | B53: TXN1055 | C53: UTILITY BILL | D53: 2187 | F53: 79760 | G53: =IF(OR(D53<>VLOOKUP(B53,Bank_Statement!B:F,3,FALSE),E53<>VLOOKUP(B53,Bank_Statement!B:F,4,FALSE)),"Mismatch","Match") -> Match | H53: =_xlfn.XLOOKUP(B53,Bank_Statement!B53:B152,Bank_Statement!F53:F152,"Not Found") -> 79760 | I53: =COUNTIF(B:B,B53) -> 1
A54: 27-04-2026 | B54: TXN1056 | C54: CHEQUE PAYMENT | D54: 4962 | F54: 74798 | G54: =IF(OR(D54<>VLOOKUP(B54,Bank_Statement!B:F,3,FALSE),E54<>VLOOKUP(B54,Bank_Statement!B:F,4,FALSE)),"Mismatch","Match") -> Match | H54: =_xlfn.XLOOKUP(B54,Bank_Statement!B54:B153,Bank_Statement!F54:F153,"Not Found") -> 74798 | I54: =COUNTIF(B:B,B54) -> 1
A55: 28-04-2026 | B55: TXN1057 | C55: CHEQUE PAYMENT | D55: 846 | F55: 73952 | G55: =IF(OR(D55<>VLOOKUP(B55,Bank_Statement!B:F,3,FALSE),E55<>VLOOKUP(B55,Bank_Statement!B:F,4,FALSE)),"Mismatch","Match") -> Match | H55: =_xlfn.XLOOKUP(B55,Bank_Statement!B55:B154,Bank_Statement!F55:F154,"Not Found") -> 73952 | I55: =COUNTIF(B:B,B55) -> 1
A56: 29-04-2026 | B56: TXN1058 | C56: NEFT CREDIT | E56: 3653 | F56: 77605 | G56: =IF(OR(D56<>VLOOKUP(B56,Bank_Statement!B:F,3,FALSE),E56<>VLOOKUP(B56,Bank_Statement!B:F,4,FALSE)),"Mismatch","Match") -> Match | H56: =_xlfn.XLOOKUP(B56,Bank_Statement!B56:B155,Bank_Statement!F56:F155,"Not Found") -> 77605 | I56: =COUNTIF(B:B,B56) -> 1
A57: 30-04-2026 | B57: TXN1059 | C57: EFT RECEIPT | E57: 7892 | F57: 85497 | G57: =IF(OR(D57<>VLOOKUP(B57,Bank_Statement!B:F,3,FALSE),E57<>VLOOKUP(B57,Bank_Statement!B:F,4,FALSE)),"Mismatch","Match") -> Match | H57: =_xlfn.XLOOKUP(B57,Bank_Statement!B57:B156,Bank_Statement!F57:F156,"Not Found") -> 85497 | I57: =COUNTIF(B:B,B57) -> 1
A58: 02-04-2026 | B58: TXN1061 | C58: CLIENT PAYMENT | E58: 9412 | F58: 103933 | G58: =IF(OR(D58<>VLOOKUP(B58,Bank_Statement!B:F,3,FALSE),E58<>VLOOKUP(B58,Bank_Statement!B:F,4,FALSE)),"Mismatch","Match") -> Match | H58: =_xlfn.XLOOKUP(B58,Bank_Statement!B58:B157,Bank_Statement!F58:F157,"Not Found") -> 103933 | I58: =COUNTIF(B:B,B58) -> 1
A59: 03-04-2026 | B59: TXN1062 | C59: NEFT CREDIT | E59: 5557 | F59: 109490 | G59: =IF(OR(D59<>VLOOKUP(B59,Bank_Statement!B:F,3,FALSE),E59<>VLOOKUP(B59,Bank_Statement!B:F,4,FALSE)),"Mismatch","Match") -> Match | H59: =_xlfn.XLOOKUP(B59,Bank_Statement!B59:B158,Bank_Statement!F59:F158,"Not Found") -> 109490 | I59: =COUNTIF(B:B,B59) -> 1
A60: 04-04-2026 | B60: TXN1063 | C60: ATM WITHDRAWAL | D60: 7443 | F60: 102047 | G60: =IF(OR(D60<>VLOOKUP(B60,Bank_Statement!B:F,3,FALSE),E60<>VLOOKUP(B60,Bank_Statement!B:F,4,FALSE)),"Mismatch","Match") -> Match | H60: =_xlfn.XLOOKUP(B60,Bank_Statement!B60:B159,Bank_Statement!F60:F159,"Not Found") -> 102047 | I60: =COUNTIF(B:B,B60) -> 1
A61: 05-04-2026 | B61: TXN1064 | C61: BANK FEES | D61: 643 | F61: 101404 | G61: =IF(OR(D61<>VLOOKUP(B61,Bank_Statement!B:F,3,FALSE),E61<>VLOOKUP(B61,Bank_Statement!B:F,4,FALSE)),"Mismatch","Match") -> Match | H61: =_xlfn.XLOOKUP(B61,Bank_Statement!B61:B160,Bank_Statement!F61:F160,"Not Found") -> 101404 | I61: =COUNTIF(B:B,B61) -> 1
A62: 06-04-2026 | B62: TXN1065 | C62: UPI RECEIPT | E62: 2139 | F62: 103543 | G62: =IF(OR(D62<>VLOOKUP(B62,Bank_Statement!B:F,3,FALSE),E62<>VLOOKUP(B62,Bank_Statement!B:F,4,FALSE)),"Mismatch","Match") -> Match | H62: =_xlfn.XLOOKUP(B62,Bank_Statement!B62:B161,Bank_Statement!F62:F161,"Not Found") -> 103543 | I62: =COUNTIF(B:B,B62) -> 1
A63: 07-04-2026 | B63: TXN1066 | C63: NEFT CREDIT | E63: 2249 | F63: 105792 | G63: =IF(OR(D63<>VLOOKUP(B63,Bank_Statement!B:F,3,FALSE),E63<>VLOOKUP(B63,Bank_Statement!B:F,4,FALSE)),"Mismatch","Match") -> Match | H63: =_xlfn.XLOOKUP(B63,Bank_Statement!B63:B162,Bank_Statement!F63:F162,"Not Found") -> 105792 | I63: =COUNTIF(B:B,B63) -> 1
A64: 08-04-2026 | B64: TXN1067 | C64: NEFT CREDIT | E64: 8692 | F64: 114484 | G64: =IF(OR(D64<>VLOOKUP(B64,Bank_Statement!B:F,3,FALSE),E64<>VLOOKUP(B64,Bank_Statement!B:F,4,FALSE)),"Mismatch","Match") -> Match | H64: =_xlfn.XLOOKUP(B64,Bank_Statement!B64:B163,Bank_Statement!F64:F163,"Not Found") -> 114484 | I64: =COUNTIF(B:B,B64) -> 1
A65: 09-04-2026 | B65: TXN1068 | C65: ATM WITHDRAWAL | D65: 2316 | F65: 112168 | G65: =IF(OR(D65<>VLOOKUP(B65,Bank_Statement!B:F,3,FALSE),E65<>VLOOKUP(B65,Bank_Statement!B:F,4,FALSE)),"Mismatch","Match") -> Match | H65: =_xlfn.XLOOKUP(B65,Bank_Statement!B65:B164,Bank_Statement!F65:F164,"Not Found") -> 112168 | I65: =COUNTIF(B:B,B65) -> 1
A66: 10-04-2026 | B66: TXN1069 | C66: EFT PAYMENT | D66: 1884 | F66: 110284 | G66: =IF(OR(D66<>VLOOKUP(B66,Bank_Statement!B:F,3,FALSE),E66<>VLOOKUP(B66,Bank_Statement!B:F,4,FALSE)),"Mismatch","Match") -> Match | H66: =_xlfn.XLOOKUP(B66,Bank_Statement!B66:B165,Bank_Statement!F66:F165,"Not Found") -> 110284 | I66: =COUNTIF(B:B,B66) -> 1
A67: 11-04-2026 | B67: TXN1070 | C67: NEFT CREDIT | E67: 816 | F67: 111100 | G67: =IF(OR(D67<>VLOOKUP(B67,Bank_Statement!B:F,3,FALSE),E67<>VLOOKUP(B67,Bank_Statement!B:F,4,FALSE)),"Mismatch","Match") -> Match | H67: =_xlfn.XLOOKUP(B67,Bank_Statement!B67:B166,Bank_Statement!F67:F166,"Not Found") -> 111100 | I67: =COUNTIF(B:B,B67) -> 1
A68: 12-04-2026 | B68: TXN1071 | C68: CHEQUE PAYMENT | D68: 4082 | F68: 107018 | G68: =IF(OR(D68<>VLOOKUP(B68,Bank_Statement!B:F,3,FALSE),E68<>VLOOKUP(B68,Bank_Statement!B:F,4,FALSE)),"Mismatch","Match") -> Match | H68: =_xlfn.XLOOKUP(B68,Bank_Statement!B68:B167,Bank_Statement!F68:F167,"Not Found") -> 107018 | I68: =COUNTIF(B:B,B68) -> 1
A69: 13-04-2026 | B69: TXN1072 | C69: UPI RECEIPT | E69: 7783 | F69: 114826 | G69: =IF(OR(D69<>VLOOKUP(B69,Bank_Statement!B:F,3,FALSE),E69<>VLOOKUP(B69,Bank_Statement!B:F,4,FALSE)),"Mismatch","Match") -> Mismatch | H69: =_xlfn.XLOOKUP(B69,Bank_Statement!B69:B168,Bank_Statement!F69:F168,"Not Found") -> 114826 | I69: =COUNTIF(B:B,B69) -> 2
A70: 14-04-2026 | B70: TXN1073 | C70: UPI RECEIPT | E70: 7180 | F70: 122006 | G70: =IF(OR(D70<>VLOOKUP(B70,Bank_Statement!B:F,3,FALSE),E70<>VLOOKUP(B70,Bank_Statement!B:F,4,FALSE)),"Mismatch","Match") -> Match | H70: =_xlfn.XLOOKUP(B70,Bank_Statement!B70:B169,Bank_Statement!F70:F169,"Not Found") -> 122006 | I70: =COUNTIF(B:B,B70) -> 1
A71: 15-04-2026 | B71: TXN1074 | C71: CHEQUE PAYMENT | D71: 5295 | F71: 116711 | G71: =IF(OR(D71<>VLOOKUP(B71,Bank_Statement!B:F,3,FALSE),E71<>VLOOKUP(B71,Bank_Statement!B:F,4,FALSE)),"Mismatch","Match") -> Match | H71: =_xlfn.XLOOKUP(B71,Bank_Statement!B71:B170,Bank_Statement!F71:F170,"Not Found") -> 116711 | I71: =COUNTIF(B:B,B71) -> 1
A72: 17-04-2026 | B72: TXN1076 | C72: CLIENT PAYMENT | E72: 8745 | F72: 130833 | G72: =IF(OR(D72<>VLOOKUP(B72,Bank_Statement!B:F,3,FALSE),E72<>VLOOKUP(B72,Bank_Statement!B:F,4,FALSE)),"Mismatch","Match") -> Match | H72: =_xlfn.XLOOKUP(B72,Bank_Statement!B72:B171,Bank_Statement!F72:F171,"Not Found") -> 130833 | I72: =COUNTIF(B:B,B72) -> 1
A73: 18-04-2026 | B73: TXN1077 | C73: ATM WITHDRAWAL | D73: 561 | F73: 130272 | G73: =IF(OR(D73<>VLOOKUP(B73,Bank_Statement!B:F,3,FALSE),E73<>VLOOKUP(B73,Bank_Statement!B:F,4,FALSE)),"Mismatch","Match") -> Match | H73: =_xlfn.XLOOKUP(B73,Bank_Statement!B73:B172,Bank_Statement!F73:F172,"Not Found") -> 130272 | I73: =COUNTIF(B:B,B73) -> 1
A74: 19-04-2026 | B74: TXN1078 | C74: BANK FEES | D74: 5575 | F74: 124697 | G74: =IF(OR(D74<>VLOOKUP(B74,Bank_Statement!B:F,3,FALSE),E74<>VLOOKUP(B74,Bank_Statement!B:F,4,FALSE)),"Mismatch","Match") -> Match | H74: =_xlfn.XLOOKUP(B74,Bank_Statement!B74:B173,Bank_Statement!F74:F173,"Not Found") -> 124697 | I74: =COUNTIF(B:B,B74) -> 1
A75: 20-04-2026 | B75: TXN1079 | C75: UPI RECEIPT | E75: 918 | F75: 125615 | G75: =IF(OR(D75<>VLOOKUP(B75,Bank_Statement!B:F,3,FALSE),E75<>VLOOKUP(B75,Bank_Statement!B:F,4,FALSE)),"Mismatch","Match") -> Match | H75: =_xlfn.XLOOKUP(B75,Bank_Statement!B75:B174,Bank_Statement!F75:F174,"Not Found") -> 125615 | I75: =COUNTIF(B:B,B75) -> 1
A76: 21-04-2026 | B76: TXN1080 | C76: UTILITY BILL | D76: 1105 | F76: 124560 | G76: =IF(OR(D76<>VLOOKUP(B76,Bank_Statement!B:F,3,FALSE),E76<>VLOOKUP(B76,Bank_Statement!B:F,4,FALSE)),"Mismatch","Match") -> Mismatch | H76: =_xlfn.XLOOKUP(B76,Bank_Statement!B76:B175,Bank_Statement!F76:F175,"Not Found") -> 124560 | I76: =COUNTIF(B:B,B76) -> 1
A77: 22-04-2026 | B77: TXN1081 | C77: UPI RECEIPT | E77: 1665 | F77: 126225 | G77: =IF(OR(D77<>VLOOKUP(B77,Bank_Statement!B:F,3,FALSE),E77<>VLOOKUP(B77,Bank_Statement!B:F,4,FALSE)),"Mismatch","Match") -> Match | H77: =_xlfn.XLOOKUP(B77,Bank_Statement!B77:B176,Bank_Statement!F77:F176,"Not Found") -> 126225 | I77: =COUNTIF(B:B,B77) -> 1
A78: 23-04-2026 | B78: TXN1072 | C78: SALARY CREDIT | E78: 9334 | F78: 135559 | G78: =IF(OR(D78<>VLOOKUP(B78,Bank_Statement!B:F,3,FALSE),E78<>VLOOKUP(B78,Bank_Statement!B:F,4,FALSE)),"Mismatch","Match") -> Mismatch | H78: =_xlfn.XLOOKUP(B78,Bank_Statement!B78:B177,Bank_Statement!F78:F177,"Not Found") -> Not Found | I78: =COUNTIF(B:B,B78) -> 2
A79: 24-04-2026 | B79: TXN1083 | C79: ATM WITHDRAWAL | D79: 3126 | F79: 132433 | G79: =IF(OR(D79<>VLOOKUP(B79,Bank_Statement!B:F,3,FALSE),E79<>VLOOKUP(B79,Bank_Statement!B:F,4,FALSE)),"Mismatch","Match") -> Match | H79: =_xlfn.XLOOKUP(B79,Bank_Statement!B79:B178,Bank_Statement!F79:F178,"Not Found") -> 132433 | I79: =COUNTIF(B:B,B79) -> 1
A80: 25-04-2026 | B80: TXN1084 | C80: CHEQUE PAYMENT | D80: 701 | F80: 131732 | G80: =IF(OR(D80<>VLOOKUP(B80,Bank_Statement!B:F,3,FALSE),E80<>VLOOKUP(B80,Bank_Statement!B:F,4,FALSE)),"Mismatch","Match") -> Match | H80: =_xlfn.XLOOKUP(B80,Bank_Statement!B80:B179,Bank_Statement!F80:F179,"Not Found") -> 131732 | I80: =COUNTIF(B:B,B80) -> 1
A81: 26-04-2026 | B81: TXN1085 | C81: BANK FEES | D81: 6151 | F81: 125581 | G81: =IF(OR(D81<>VLOOKUP(B81,Bank_Statement!B:F,3,FALSE),E81<>VLOOKUP(B81,Bank_Statement!B:F,4,FALSE)),"Mismatch","Match") -> Match | H81: =_xlfn.XLOOKUP(B81,Bank_Statement!B81:B180,Bank_Statement!F81:F180,"Not Found") -> 125581 | I81: =COUNTIF(B:B,B81) -> 1
A82: 27-04-2026 | B82: TXN1086 | C82: UPI RECEIPT | E82: 4690 | F82: 130271 | G82: =IF(OR(D82<>VLOOKUP(B82,Bank_Statement!B:F,3,FALSE),E82<>VLOOKUP(B82,Bank_Statement!B:F,4,FALSE)),"Mismatch","Match") -> Match | H82: =_xlfn.XLOOKUP(B82,Bank_Statement!B82:B181,Bank_Statement!F82:F181,"Not Found") -> 130271 | I82: =COUNTIF(B:B,B82) -> 1
A83: 28-04-2026 | B83: TXN1087 | C83: EFT PAYMENT | D83: 992 | F83: 129279 | G83: =IF(OR(D83<>VLOOKUP(B83,Bank_Statement!B:F,3,FALSE),E83<>VLOOKUP(B83,Bank_Statement!B:F,4,FALSE)),"Mismatch","Match") -> Match | H83: =_xlfn.XLOOKUP(B83,Bank_Statement!B83:B182,Bank_Statement!F83:F182,"Not Found") -> 129279 | I83: =COUNTIF(B:B,B83) -> 1
A84: 29-04-2026 | B84: TXN1088 | C84: SALARY CREDIT | E84: 6022 | F84: 135301 | G84: =IF(OR(D84<>VLOOKUP(B84,Bank_Statement!B:F,3,FALSE),E84<>VLOOKUP(B84,Bank_Statement!B:F,4,FALSE)),"Mismatch","Match") -> Match | H84: =_xlfn.XLOOKUP(B84,Bank_Statement!B84:B183,Bank_Statement!F84:F183,"Not Found") -> 135301 | I84: =COUNTIF(B:B,B84) -> 1
A85: 30-04-2026 | B85: TXN1089 | C85: NEFT CREDIT | E85: 5013 | F85: 140314 | G85: =IF(OR(D85<>VLOOKUP(B85,Bank_Statement!B:F,3,FALSE),E85<>VLOOKUP(B85,Bank_Statement!B:F,4,FALSE)),"Mismatch","Match") -> Match | H85: =_xlfn.XLOOKUP(B85,Bank_Statement!B85:B184,Bank_Statement!F85:F184,"Not Found") -> 140314 | I85: =COUNTIF(B:B,B85) -> 1
A86: 02-04-2026 | B86: TXN1091 | C86: EFT RECEIPT | E86: 8977 | F86: 158565 | G86: =IF(OR(D86<>VLOOKUP(B86,Bank_Statement!B:F,3,FALSE),E86<>VLOOKUP(B86,Bank_Statement!B:F,4,FALSE)),"Mismatch","Match") -> Match | H86: =_xlfn.XLOOKUP(B86,Bank_Statement!B86:B185,Bank_Statement!F86:F185,"Not Found") -> 158565 | I86: =COUNTIF(B:B,B86) -> 1
A87: 03-04-2026 | B87: TXN1092 | C87: SALARY CREDIT | E87: 3211 | F87: 161776 | G87: =IF(OR(D87<>VLOOKUP(B87,Bank_Statement!B:F,3,FALSE),E87<>VLOOKUP(B87,Bank_Statement!B:F,4,FALSE)),"Mismatch","Match") -> Match | H87: =_xlfn.XLOOKUP(B87,Bank_Statement!B87:B186,Bank_Statement!F87:F186,"Not Found") -> 161776 | I87: =COUNTIF(B:B,B87) -> 1
A88: 04-04-2026 | B88: TXN1093 | C88: BANK FEES | D88: 993 | F88: 160783 | G88: =IF(OR(D88<>VLOOKUP(B88,Bank_Statement!B:F,3,FALSE),E88<>VLOOKUP(B88,Bank_Statement!B:F,4,FALSE)),"Mismatch","Match") -> Match | H88: =_xlfn.XLOOKUP(B88,Bank_Statement!B88:B187,Bank_Statement!F88:F187,"Not Found") -> 160783 | I88: =COUNTIF(B:B,B88) -> 1
A89: 05-04-2026 | B89: TXN1094 | C89: CHEQUE PAYMENT | D89: 6193 | F89: 154590 | G89: =IF(OR(D89<>VLOOKUP(B89,Bank_Statement!B:F,3,FALSE),E89<>VLOOKUP(B89,Bank_Statement!B:F,4,FALSE)),"Mismatch","Match") -> Match | H89: =_xlfn.XLOOKUP(B89,Bank_Statement!B89:B188,Bank_Statement!F89:F188,"Not Found") -> 154590 | I89: =COUNTIF(B:B,B89) -> 1
A90: 06-04-2026 | B90: TXN1095 | C90: UTILITY BILL | D90: 7225 | F90: 147365 | G90: =IF(OR(D90<>VLOOKUP(B90,Bank_Statement!B:F,3,FALSE),E90<>VLOOKUP(B90,Bank_Statement!B:F,4,FALSE)),"Mismatch","Match") -> Match | H90: =_xlfn.XLOOKUP(B90,Bank_Statement!B90:B189,Bank_Statement!F90:F189,"Not Found") -> 147365 | I90: =COUNTIF(B:B,B90) -> 1
A91: 07-04-2026 | B91: TXN1096 | C91: UTILITY BILL | D91: 7022 | F91: 140343 | G91: =IF(OR(D91<>VLOOKUP(B91,Bank_Statement!B:F,3,FALSE),E91<>VLOOKUP(B91,Bank_Statement!B:F,4,FALSE)),"Mismatch","Match") -> Match | H91: =_xlfn.XLOOKUP(B91,Bank_Statement!B91:B190,Bank_Statement!F91:F190,"Not Found") -> 140343 | I91: =COUNTIF(B:B,B91) -> 1
A92: 08-04-2026 | B92: TXN1097 | C92: CLIENT PAYMENT | E92: 3312 | F92: 143655 | G92: =IF(OR(D92<>VLOOKUP(B92,Bank_Statement!B:F,3,FALSE),E92<>VLOOKUP(B92,Bank_Statement!B:F,4,FALSE)),"Mismatch","Match") -> Match | H92: =_xlfn.XLOOKUP(B92,Bank_Statement!B92:B191,Bank_Statement!F92:F191,"Not Found") -> 143655 | I92: =COUNTIF(B:B,B92) -> 1
A93: 09-04-2026 | B93: TXN1098 | C93: NEFT CREDIT | E93: 8306 | F93: 151961 | G93: =IF(OR(D93<>VLOOKUP(B93,Bank_Statement!B:F,3,FALSE),E93<>VLOOKUP(B93,Bank_Statement!B:F,4,FALSE)),"Mismatch","Match") -> Match | H93: =_xlfn.XLOOKUP(B93,Bank_Statement!B93:B192,Bank_Statement!F93:F192,"Not Found") -> 151961 | I93: =COUNTIF(B:B,B93) -> 1
A94: 10-04-2026 | B94: TXN1099 | C94: EFT RECEIPT | E94: 7877 | F94: 159838 | G94: =IF(OR(D94<>VLOOKUP(B94,Bank_Statement!B:F,3,FALSE),E94<>VLOOKUP(B94,Bank_Statement!B:F,4,FALSE)),"Mismatch","Match") -> Match | H94: =_xlfn.XLOOKUP(B94,Bank_Statement!B94:B193,Bank_Statement!F94:F193,"Not Found") -> 159838 | I94: =COUNTIF(B:B,B94) -> 1

Sheet Tasks
A1: Tasks
A3: 1. Find missing transactions between Bank Statement and Cash Book.
A4: 2. Use VLOOKUP/XLOOKUP to match Transaction IDs.
A5: 3. Highlight mismatched amounts using Conditional Formatting.
A6: 4. Use IF formula to classify transactions as Match/Mismatch.
A7: 5. Create Pivot Table for Debit and Credit totals.
A8: 6. Find duplicate Transaction IDs using COUNTIF.
A9: 7. Filter only unmatched transactions.
A10: 8. Calculate total Debit and Credit amounts using SUMIF.
A11: 9. Identify timing differences.
A12: 10. Prepare a basic reconciliation summary.
